nanomesh/__init__.py
nanomesh/_constants.py
nanomesh/_doc.py
nanomesh/_tetgen_wrapper.py
nanomesh/_triangle_wrapper.py
nanomesh/io.py
nanomesh/mesh_container.py
nanomesh/metrics.py
nanomesh/region_markers.py
nanomesh/utils.py
nanomesh/data/__init__.py
nanomesh/data/nanopores3d.npy
nanomesh/data/nanopores_gradient.npy
nanomesh/image/__init__.py
nanomesh/image/_image.py
nanomesh/image/_plane.py
nanomesh/image/_roi2d.py
nanomesh/image/_utils.py
nanomesh/image/_volume.py
nanomesh/image2mesh/__init__.py
nanomesh/image2mesh/_mesher.py
nanomesh/image2mesh/_mesher2d/__init__.py
nanomesh/image2mesh/_mesher2d/_helpers.py
nanomesh/image2mesh/_mesher2d/_mesher.py
nanomesh/image2mesh/_mesher2d/_polygon.py
nanomesh/image2mesh/_mesher3d/__init__.py
nanomesh/image2mesh/_mesher3d/_bounding_box.py
nanomesh/image2mesh/_mesher3d/_helpers.py
nanomesh/image2mesh/_mesher3d/_mesher.py
nanomesh/mesh/__init__.py
nanomesh/mesh/_line.py
nanomesh/mesh/_mesh.py
nanomesh/mesh/_mixin.py
nanomesh/mesh/_tetra.py
nanomesh/mesh/_triangle.py
nanomesh/plotting/__init__.py
nanomesh/plotting/_meshplot.py
nanomesh/plotting/_widgets.py
nanomesh-0.9.1.dist-info/LICENSE
nanomesh-0.9.1.dist-info/METADATA
nanomesh-0.9.1.dist-info/WHEEL
nanomesh-0.9.1.dist-info/top_level.txt
nanomesh-0.9.1.dist-info/RECORD
