Metadata-Version: 2.1
Name: nanomesh
Version: 0.9.1
Summary: Creates 3d meshes from microscopy experimental data
Home-page: https://github.com/hpgem/nanomesh
Author: Nicolas Renaud
Author-email: n.renaud@esciencecenter.nl
License: UNKNOWN
Project-URL: Bug Tracker, https://github.com/hpgem/nanomesh/issues
Keywords: materials-science,mesh-generation,microscopy
Platform: UNKNOWN
Classifier: Development Status :: 2 - Pre-Alpha
Classifier: Intended Audience :: Developers
Classifier: License :: OSI Approved :: Apache Software License
Classifier: Natural Language :: English
Classifier: Programming Language :: Python :: 3
Classifier: Programming Language :: Python :: 3.8
Classifier: Programming Language :: Python :: 3.9
Requires-Dist: IPython (!=7.23)
Requires-Dist: ipywidgets
Requires-Dist: itkwidgets
Requires-Dist: matplotlib (>=3.5)
Requires-Dist: meshio (>=5.3)
Requires-Dist: numpy
Requires-Dist: pyvista
Requires-Dist: scikit-image
Requires-Dist: scikit-learn
Requires-Dist: scipy
Requires-Dist: triangle
Provides-Extra: develop
Requires-Dist: bump2version ; extra == 'develop'
Requires-Dist: isort ; extra == 'develop'
Requires-Dist: pre-commit ; extra == 'develop'
Requires-Dist: yapf ; extra == 'develop'
Requires-Dist: nbmake ; extra == 'develop'
Requires-Dist: pytest ; extra == 'develop'
Requires-Dist: pytest-cov ; extra == 'develop'
Requires-Dist: pycodestyle ; extra == 'develop'
Requires-Dist: jupytext ; extra == 'develop'
Requires-Dist: nbsphinx ; extra == 'develop'
Requires-Dist: nbsphinx-link ; extra == 'develop'
Requires-Dist: recommonmark ; extra == 'develop'
Requires-Dist: sphinx ; extra == 'develop'
Requires-Dist: sphinx-rtd-theme ; extra == 'develop'
Requires-Dist: autodocsumm ; extra == 'develop'
Provides-Extra: publishing
Requires-Dist: twine ; extra == 'publishing'
Requires-Dist: wheel ; extra == 'publishing'
